MANIFEST.in
setup.py
etc/vogeler/vogeler.conf
etc/vogeler/_design/system_records/views/all/map.js
etc/vogeler/_design/system_records/views/by_name/map.js
etc/vogeler/_design/system_records/views/packages_by_host/map.js
etc/vogeler/plugins/facter.cfg
etc/vogeler/plugins/ohai.cfg
etc/vogeler/plugins/ps.cfg
etc/vogeler/plugins/rpms.cfg
scripts/vogeler-client
scripts/vogeler-runner
scripts/vogeler-server
vogeler/__init__.py
vogeler/client.py
vogeler/conf.py
vogeler/encryption.py
vogeler/exceptions.py
vogeler/log.py
vogeler/logger.py
vogeler/messaging.py
vogeler/persistence.py
vogeler/plugins.py
vogeler/runner.py
vogeler/server.py
vogeler.egg-info/PKG-INFO
vogeler.egg-info/SOURCES.txt
vogeler.egg-info/dependency_links.txt
vogeler.egg-info/requires.txt
vogeler.egg-info/top_level.txt
vogeler/db/__init__.py
vogeler/db/couch.py
vogeler/db/generic.py
vogeler/queue/__init__.py
vogeler/queue/amqp.py
vogeler/queue/generic.py