Metadata-Version: 1.0
Name: vogeler
Version: 0.9.2
Summary: Python-based CMDB Framework
Home-page: http://lusis.github.com/vogeler
Author: John E. Vincent
Author-email: lusis.org+github.com@gmail.com
License: UNKNOWN
Keywords: cmdb
Platform: UNKNOWN
Classifier: Development Status :: 4 - Beta
Classifier: Environment :: Console
Classifier: Intended Audience :: System Administrators
Classifier: License :: OSI Approved :: GNU General Public License (GPL)
Classifier: Natural Language :: English
Classifier: Programming Language :: Python :: 2.6
Classifier: Programming Language :: Python :: 2.7
Classifier: Topic :: System :: Systems Administration
Classifier: Operating System :: POSIX :: Linux
